sudoku_mip_solver/__init__.py
sudoku_mip_solver/__main__.py
sudoku_mip_solver/cli.py
sudoku_mip_solver/sudoku_mip_solver.py
sudoku_mip_solver-0.2.0.dist-info/licenses/LICENSE
sudoku_mip_solver-0.2.0.dist-info/METADATA
sudoku_mip_solver-0.2.0.dist-info/WHEEL
sudoku_mip_solver-0.2.0.dist-info/entry_points.txt
sudoku_mip_solver-0.2.0.dist-info/top_level.txt
sudoku_mip_solver-0.2.0.dist-info/RECORD
