Metadata-Version: 2.4
Name: sudoku-mip-solver
Version: 0.2.0
Summary: A Sudoku puzzle solver and generator using Mixed Integer Programming (MIP)
Author: Rasmus Ørnstrup Mikkelsen
License: MIT License
Project-URL: Homepage, https://github.com/DenHvideDvaerg/sudoku-mip-solver
Project-URL: Bug Tracker, https://github.com/DenHvideDvaerg/sudoku-mip-solver/issues
Classifier: Programming Language :: Python :: 3
Classifier: Programming Language :: Python :: 3.9
Classifier: Programming Language :: Python :: 3.10
Classifier: Programming Language :: Python :: 3.11
Classifier: License :: OSI Approved :: MIT License
Classifier: Operating System :: OS Independent
Classifier: Topic :: Games/Entertainment :: Puzzle Games
Classifier: Topic :: Scientific/Engineering :: Mathematics
Requires-Python: >=3.9
License-File: LICENSE
Requires-Dist: pulp>=3.1.1
Dynamic: license-file
